[
    {
        "key": "dbln",
        "value": "%7B%2261577390076403%22%3A%2268HIH1hC%22%2C%2261578336149942%22%3A%22BMNAPmMc%22%7D",
        "domain": "facebook.com",
        "path": "/login/device-based/",
        "hostOnly": false,
        "creation": "2025-07-24T15:38:32.900Z",
        "lastAccessed": "2025-07-24T15:38:32.900Z"
    },
    {
        "key": "datr",
        "value": "MBtVaEwPIWATm8siOtLi2Kts",
        "domain": "facebook.com",
        "path": "/",
        "hostOnly": false,
        "creation": "2025-07-24T15:38:32.900Z",
        "lastAccessed": "2025-07-24T15:38:32.900Z"
    },
    {
        "key": "sb",
        "value": "MBtVaM_HYTlcG2AQPB1r35Rv",
        "domain": "facebook.com",
        "path": "/",
        "hostOnly": false,
        "creation": "2025-07-24T15:38:32.900Z",
        "lastAccessed": "2025-07-24T15:38:32.900Z"
    },
    {
        "key": "vpd",
        "value": "v1%3B688x360x3",
        "domain": "facebook.com",
        "path": "/",
        "hostOnly": false,
        "creation": "2025-07-24T15:38:32.900Z",
        "lastAccessed": "2025-07-24T15:38:32.900Z"
    },
    {
        "key": "ps_l",
        "value": "1",
        "domain": "facebook.com",
        "path": "/",
        "hostOnly": false,
        "creation": "2025-07-24T15:38:32.900Z",
        "lastAccessed": "2025-07-24T15:38:32.900Z"
    },
    {
        "key": "ps_n",
        "value": "1",
        "domain": "facebook.com",
        "path": "/",
        "hostOnly": false,
        "creation": "2025-07-24T15:38:32.900Z",
        "lastAccessed": "2025-07-24T15:38:32.900Z"
    },
    {
        "key": "c_user",
        "value": "61578336149942",
        "domain": "facebook.com",
        "path": "/",
        "hostOnly": false,
        "creation": "2025-07-24T15:38:32.900Z",
        "lastAccessed": "2025-07-24T15:38:32.900Z"
    },
    {
        "key": "xs",
        "value": "22%3As4zVVKv4l-wJKA%3A2%3A1752494096%3A-1%3A-1",
        "domain": "facebook.com",
        "path": "/",
        "hostOnly": false,
        "creation": "2025-07-24T15:38:32.900Z",
        "lastAccessed": "2025-07-24T15:38:32.900Z"
    },
    {
        "key": "pas",
        "value": "61577390076403%3ACoegeBWr4D%2C61578336149942%3A3yqheVayB8",
        "domain": "facebook.com",
        "path": "/",
        "hostOnly": false,
        "creation": "2025-07-24T15:38:32.900Z",
        "lastAccessed": "2025-07-24T15:38:32.900Z"
    },
    {
        "key": "locale",
        "value": "en_GB",
        "domain": "facebook.com",
        "path": "/",
        "hostOnly": false,
        "creation": "2025-07-24T15:38:32.900Z",
        "lastAccessed": "2025-07-24T15:38:32.900Z"
    },
    {
        "key": "fr",
        "value": "08VbCzve1AuZvpqus.AWf7pmb5jeLmEN2YhZJNVWH8pImnP-N3mSECk_kXnGUpvMR_VvM.BoVRsw..AAA.0.0.BoglNn.AWfbqFVSx3cRMZ9o6Y0qQn3B7Rc",
        "domain": "facebook.com",
        "path": "/",
        "hostOnly": false,
        "creation": "2025-07-24T15:38:32.900Z",
        "lastAccessed": "2025-07-24T15:38:32.900Z"
    },
    {
        "key": "fbl_st",
        "value": "101523624%3BT%3A29222858",
        "domain": "facebook.com",
        "path": "/",
        "hostOnly": false,
        "creation": "2025-07-24T15:38:32.900Z",
        "lastAccessed": "2025-07-24T15:38:32.900Z"
    },
    {
        "key": "wl_cbv",
        "value": "v2%3Bclient_version%3A2878%3Btimestamp%3A1753371496",
        "domain": "facebook.com",
        "path": "/",
        "hostOnly": false,
        "creation": "2025-07-24T15:38:32.900Z",
        "lastAccessed": "2025-07-24T15:38:32.900Z"
    }
]
